<nfdrs>
<row num="1">
<sta_id>44914</sta_id>
<sta_nm>LA PANZA</sta_nm>
<nfdr_dt>051015</nfdr_dt>
<nfdr_tm>13</nfdr_tm>
<nfdr_type>F</nfdr_type>
<mp>1</mp>
<msgc>7G3A2</msgc>
<one_hr>3</one_hr>
<ten_hr>5</ten_hr>
<hu_hr>11</hu_hr>
<th_hr>11</th_hr>
<xh_hr>9</xh_hr>
<ic>63</ic>
<kbdi>599</kbdi>
<sc>21</sc>
<ec>60</ec>
<bi>81</bi>
<sl>5 </sl>
<lr>0</lr>
<lo>0</lo>
<hr/>0
      <ho>0</ho>
<fl>57</fl>
<hrb>3</hrb>
<wdy>82</wdy>
<adj>V </adj>
</row>
<row num="2">
<sta_id>44914</sta_id>
<sta_nm>LA PANZA</sta_nm>
<nfdr_dt>050915</nfdr_dt>
<nfdr_tm>13</nfdr_tm>
<nfdr_type>F</nfdr_type>
<mp>1</mp>
<msgc>7G3A2</msgc>
<one_hr>5</one_hr>
<ten_hr>7</ten_hr>
<hu_hr>11</hu_hr>
<th_hr>11</th_hr>
<xh_hr>9</xh_hr>
<ic>27</ic>
<kbdi>598</kbdi>
<sc>8</sc>
<ec>58</ec>
<bi>49</bi>
<sl>4 </sl>
<lr>0</lr>
<lo>0</lo>
<hr/>0
      <ho>0</ho>
<fl>35</fl>
<hrb>5</hrb>
<wdy>82</wdy>
<adj>H </adj>
</row>
<row num="3">
<sta_id>44914</sta_id>
<sta_nm>LA PANZA</sta_nm>
<nfdr_dt>050915</nfdr_dt>
<nfdr_tm>6</nfdr_tm>
<nfdr_type>N</nfdr_type>
<mp>1</mp>
<msgc>7G3A2</msgc>
<one_hr>21</one_hr>
<ten_hr>16</ten_hr>
<hu_hr>12</hu_hr>
<th_hr>11</th_hr>
<xh_hr>9</xh_hr>
<ic>0</ic>
<kbdi>598</kbdi>
<sc>3</sc>
<ec>42</ec>
<bi>28</bi>
<sl>1 </sl>
<lr>0</lr>
<lo>0</lo>
<hr/>0
      <ho>0</ho>
<fl>20</fl>
<hrb>21</hrb>
<wdy>81</wdy>
<adj>L </adj>
</row>
<row num="4">
<sta_id>44914</sta_id>
<sta_nm>LA PANZA</sta_nm>
<nfdr_dt>050915</nfdr_dt>
<nfdr_tm>0</nfdr_tm>
<nfdr_type>N</nfdr_type>
<mp>1</mp>
<msgc>7G3A2</msgc>
<one_hr>20</one_hr>
<ten_hr>14</ten_hr>
<hu_hr>12</hu_hr>
<th_hr>11</th_hr>
<xh_hr>9</xh_hr>
<ic>0</ic>
<kbdi>598</kbdi>
<sc>3</sc>
<ec>43</ec>
<bi>30</bi>
<sl>1 </sl>
<lr>0</lr>
<lo>0</lo>
<hr/>0
      <ho>0</ho>
<fl>21</fl>
<hrb>20</hrb>
<wdy>81</wdy>
<adj>L </adj>
</row>
<row num="5">
<sta_id>44914</sta_id>
<sta_nm>LA PANZA</sta_nm>
<nfdr_dt>050915</nfdr_dt>
<nfdr_tm>12</nfdr_tm>
<nfdr_type>N</nfdr_type>
<mp>1</mp>
<msgc>7G3A2</msgc>
<one_hr>10</one_hr>
<ten_hr>11</ten_hr>
<hu_hr>12</hu_hr>
<th_hr>11</th_hr>
<xh_hr>9</xh_hr>
<ic>8</ic>
<kbdi>599</kbdi>
<sc>11</sc>
<ec>51</ec>
<bi>56</bi>
<sl>4 </sl>
<lr>0</lr>
<lo>0</lo>
<hr/>0
      <ho>0</ho>
<fl>40</fl>
<hrb>10</hrb>
<wdy>83</wdy>
<adj>M </adj>
</row>
<row num="6">
<sta_id>44914</sta_id>
<sta_nm>LA PANZA</sta_nm>
<nfdr_dt>050915</nfdr_dt>
<nfdr_tm>18</nfdr_tm>
<nfdr_type>N</nfdr_type>
<mp>1</mp>
<msgc>7G3A2</msgc>
<one_hr>8</one_hr>
<ten_hr>9</ten_hr>
<hu_hr>12</hu_hr>
<th_hr>11</th_hr>
<xh_hr>9</xh_hr>
<ic>11</ic>
<kbdi>599</kbdi>
<sc>10</sc>
<ec>53</ec>
<bi>54</bi>
<sl>4 </sl>
<lr>0</lr>
<lo>0</lo>
<hr/>0
      <ho>0</ho>
<fl>38</fl>
<hrb>8</hrb>
<wdy>83</wdy>
<adj>M </adj>
</row>
<row num="7">
<sta_id>44914</sta_id>
<sta_nm>LA PANZA</sta_nm>
<nfdr_dt>050915</nfdr_dt>
<nfdr_tm>12</nfdr_tm>
<nfdr_type>O</nfdr_type>
<mp>1</mp>
<msgc>7G3A2</msgc>
<one_hr>5</one_hr>
<ten_hr>7</ten_hr>
<hu_hr>12</hu_hr>
<th_hr>11</th_hr>
<xh_hr>9</xh_hr>
<ic>37</ic>
<kbdi>599</kbdi>
<sc>14</sc>
<ec>56</ec>
<bi>65</bi>
<sl>4 </sl>
<lr>0</lr>
<lo>0</lo>
<hr/>0
      <ho>0</ho>
<fl>46</fl>
<hrb>5</hrb>
<wdy>83</wdy>
<adj>H </adj>
</row>
<row num="8">
<sta_id>44914</sta_id>
<sta_nm>LA PANZA</sta_nm>
<nfdr_dt>050915</nfdr_dt>
<nfdr_tm>8</nfdr_tm>
<nfdr_type>S</nfdr_type>
<mp>1</mp>
<msgc>7G3A2</msgc>
<one_hr>9</one_hr>
<ten_hr>10</ten_hr>
<hu_hr>12</hu_hr>
<th_hr>11</th_hr>
<xh_hr>9</xh_hr>
<ic>11</ic>
<kbdi>598</kbdi>
<sc>6</sc>
<ec>51</ec>
<bi>43</bi>
<sl>4 </sl>
<lr>0</lr>
<lo>0</lo>
<hr/>0
      <ho>0</ho>
<fl>30</fl>
<hrb>9</hrb>
<wdy>83</wdy>
<adj>M </adj>
</row>
</nfdrs>